[
  {
    "question": "The duration of Medieval Period was from ___ Century C.E to ___ Century C.E.",
    "choice1": "4th, 8th",
    "choice2": "10th, 20th",
    "choice3": "5th, 15th",
    "choice4": "4th, 15th",
    "answer": 3,
    "explanation": "The duration of the Medival period was from fifth century to fifteenth century CE. Eventhough the political structure of the medival period was similar, the term Medival period was not refered as the same period all over the world."
  },
  {
    "question": "Which of these was the largest ancient empire?",
    "choice1": "The Chinese Empire",
    "choice2": "The Roman Empire",
    "choice3": "The Frankish Empire",
    "choice4": "The Mongol Empire",
    "answer": 2,
    "explanation": "Among the ancient empires The Roman empire was the largest empire."
  },
  {
    "question": "Who divided the Roman Empire into 2 in the 4th Century C.E?",
    "choice1": "Justinian",
    "choice2": "Diocletian",
    "choice3": "Sulaiman",
    "choice4": "Charlemagne",
    "answer": 2,
    "explanation": ""
  },
  {
    "question": "Which of these was the capital of Eastern Roman Empire?",
    "choice1": "Constantinople",
    "choice2": "Rome",
    "choice3": "Damascus",
    "choice4": "Timbuktu",
    "answer": 1,
    "explanation": ""
  },
  {
    "question": "Constantinople was also known as ________",
    "choice1": "Baghdad",
    "choice2": "Byzantium",
    "choice3": "Mecca",
    "choice4": "Siberia",
    "answer": 2,
    "explanation": ""
  },
  {
    "question": "'History will judiciously forget the wars of Justinian and remember him for his laws.'  -whose words are these?",
    "choice1": "St. Augustine",
    "choice2": "Ibn Khaldun",
    "choice3": "Will Durant",
    "choice4": "Kalhana",
    "answer": 3,
    "explanation": ""
  },
  {
    "question": "What was the Code of Law made by Justinian?",
    "choice1": "Corpus Juris Civilis",
    "choice2": "Republic",
    "choice3": "Democracy",
    "choice4": "Sociare Corpus",
    "answer": 1,
    "explanation": ""
  },
  {
    "question": "Who codified the code of law,'Corpus Juris Civilis'?",
    "choice1": "Sulaiman",
    "choice2": "Diocletian",
    "choice3": "Charlemagne",
    "choice4": "Justinian",
    "answer": 4,
    "explanation": ""
  },
  {
    "question": "What was 'Corpus Juris Civilis' based on?",
    "choice1": "Reasoning, Justice, and generosity",
    "choice2": "",
    "choice3": "",
    "choice4": "",
    "answer": 1,
    "explanation": ""
  },
  {
    "question": "Which French ruler adopted the Justinian's code of laws for administration?",
    "choice1": "Henty IV",
    "choice2": "Napolean",
    "choice3": "Louis XIV",
    "choice4": "Charlemagne",
    "answer": 2,
    "explanation": ""
  },
  {
    "question": "Who captured Constantinople in the 15th Century C.E which led to the decline of Eastern Roman Empire?",
    "choice1": "The Arabs",
    "choice2": "The Mongols",
    "choice3": "The Turks",
    "choice4": "The Chinese",
    "answer": 3,
    "explanation": ""
  }
]
